bithuman/__init__.py
bithuman/_version.py
bithuman/api.py
bithuman/config.py
bithuman/runtime.py
bithuman/runtime_async.py
bithuman/audio/__init__.py
bithuman/audio/audio.py
bithuman/audio/hparams.py
bithuman/audio/utils.py
bithuman/lib/__init__.py
bithuman/lib/_bithuman_py.cpython-312-darwin.so
bithuman/lib/_bithuman_py.pyi
bithuman/lib/audio_encoder.onnx
bithuman/lib/generator.py
bithuman/lib/pth2h5.py
bithuman/plugins/__init__.py
bithuman/plugins/stt.py
bithuman/service/__init__.py
bithuman/service/client.py
bithuman/service/messages.py
bithuman/service/server.py
bithuman/utils/__init__.py
bithuman/utils/agent.py
bithuman/utils/fps_controller.py
bithuman/utils/image.py
bithuman/utils/unzip.py
bithuman/video_graph/__init__.py
bithuman/video_graph/action_trigger.py
bithuman/video_graph/driver_video.py
bithuman/video_graph/navigator.py
bithuman/video_graph/trigger.py
bithuman/video_graph/video_script.py
bithuman-0.11.4.dist-info/METADATA
bithuman-0.11.4.dist-info/WHEEL
bithuman-0.11.4.dist-info/top_level.txt
bithuman-0.11.4.dist-info/RECORD
