Metadata-Version: 2.4
Name: bithuman
Version: 0.11.4
Summary: Bithuman library
Platform: Linux
Platform: Mac OS X
Platform: Windows
Requires-Python: >=3.9
Requires-Dist: numpy>=1.26.0
Requires-Dist: h5py~=3.13
Requires-Dist: loguru~=0.7
Requires-Dist: numba<1.0,>=0.60
Requires-Dist: soxr~=0.5
Requires-Dist: scipy<2.0,>=1.13
Requires-Dist: moviepy~=1.0.3
Requires-Dist: soundfile~=0.13
Requires-Dist: pydantic~=2.10
Requires-Dist: pydantic-settings~=2.8
Requires-Dist: networkx<4.0,>=3.1
Requires-Dist: tqdm~=4.67
Requires-Dist: dataclasses-json~=0.6
Requires-Dist: librosa~=0.10
Requires-Dist: pyzmq~=26.2; python_version < "3.14"
Requires-Dist: msgpack~=1.1
Requires-Dist: PyYAML~=6.0
Requires-Dist: aiohttp~=3.11
Requires-Dist: onnxruntime==1.20.1
Provides-Extra: agent
Requires-Dist: livekit-agents~=1.1; extra == "agent"
Dynamic: platform
Dynamic: requires-python
